GoBianchengShiguang/README.md
GoBianchengShiguang/__init__.py
GoBianchengShiguang/__main__.py
GoBianchengShiguang/file.epub
GoBianchengShiguang/index.html
GoBianchengShiguang/css/__init__.py
GoBianchengShiguang/css/annotations.css
GoBianchengShiguang/css/main.css
GoBianchengShiguang/css/normalize.css
GoBianchengShiguang/css/popup.css
GoBianchengShiguang/font/__init__.py
GoBianchengShiguang/font/fontello.eot
GoBianchengShiguang/font/fontello.svg
GoBianchengShiguang/font/fontello.ttf
GoBianchengShiguang/font/fontello.woff
GoBianchengShiguang/img/__init__.py
GoBianchengShiguang/img/annotator-glyph-sprite.png
GoBianchengShiguang/img/annotator-icon-sprite.png
GoBianchengShiguang/img/apple-touch-icon.png
GoBianchengShiguang/img/cancelfullscreen.png
GoBianchengShiguang/img/close.png
GoBianchengShiguang/img/fullscreen.png
GoBianchengShiguang/img/loader.gif
GoBianchengShiguang/img/menu-icon.png
GoBianchengShiguang/img/save.png
GoBianchengShiguang/img/saved.png
GoBianchengShiguang/img/settings-s.png
GoBianchengShiguang/img/settings.png
GoBianchengShiguang/img/star.png
GoBianchengShiguang/js/__init__.py
GoBianchengShiguang/js/epub.js
GoBianchengShiguang/js/epub.min.js
GoBianchengShiguang/js/epub.min.map
GoBianchengShiguang/js/hooks.min.js
GoBianchengShiguang/js/hooks.min.map
GoBianchengShiguang/js/reader.js
GoBianchengShiguang/js/reader.js.map
GoBianchengShiguang/js/reader.min.js
GoBianchengShiguang/js/reader.min.map
GoBianchengShiguang/js/hooks/__init__.py
GoBianchengShiguang/js/hooks/extensions/__init__.py
GoBianchengShiguang/js/hooks/extensions/highlight.js
GoBianchengShiguang/js/libs/__init__.py
GoBianchengShiguang/js/libs/jquery.min.js
GoBianchengShiguang/js/libs/localforage.min.js
GoBianchengShiguang/js/libs/screenfull.js
GoBianchengShiguang/js/libs/screenfull.min.js
GoBianchengShiguang/js/libs/zip.min.js
GoBianchengShiguang/js/plugins/__init__.py
GoBianchengShiguang/js/plugins/hypothesis.js
GoBianchengShiguang/js/plugins/search.js
go_biancheng_shiguang-2024.3.6.0.dist-info/METADATA
go_biancheng_shiguang-2024.3.6.0.dist-info/WHEEL
go_biancheng_shiguang-2024.3.6.0.dist-info/entry_points.txt
go_biancheng_shiguang-2024.3.6.0.dist-info/top_level.txt
go_biancheng_shiguang-2024.3.6.0.dist-info/RECORD
